{
"meta":{"test_sets":[],"test_metrics":[],"learn_metrics":[{"best_value":"Min","name":"Logloss"}],"launch_mode":"Train","parameters":"","iteration_count":100,"learn_sets":["learn"],"name":"experiment"},
"iterations":[
{"learn":[0.4374900567],"iteration":0,"passed_time":0.05923328993,"remaining_time":5.864095703},
{"learn":[0.2864055604],"iteration":1,"passed_time":0.06736897934,"remaining_time":3.301079988},
{"learn":[0.2243506831],"iteration":2,"passed_time":0.07310272725,"remaining_time":2.363654848},
{"learn":[0.1891654858],"iteration":3,"passed_time":0.08085665371,"remaining_time":1.940559689},
{"learn":[0.1768107118],"iteration":4,"passed_time":0.08564094129,"remaining_time":1.627177884},
{"learn":[0.162462723],"iteration":5,"passed_time":0.09256822466,"remaining_time":1.45023552},
{"learn":[0.1490030989],"iteration":6,"passed_time":0.09873805302,"remaining_time":1.311805562},
{"learn":[0.1398177708],"iteration":7,"passed_time":0.1088751855,"remaining_time":1.252064634},
{"learn":[0.1341085552],"iteration":8,"passed_time":0.1169451623,"remaining_time":1.18244553},
{"learn":[0.1315538488],"iteration":9,"passed_time":0.1251143116,"remaining_time":1.126028805},
{"learn":[0.1270795664],"iteration":10,"passed_time":0.132840033,"remaining_time":1.07479663},
{"learn":[0.1262669775],"iteration":11,"passed_time":0.1447605597,"remaining_time":1.061577438},
{"learn":[0.1224434437],"iteration":12,"passed_time":0.1515733939,"remaining_time":1.01437579},
{"learn":[0.1196647745],"iteration":13,"passed_time":0.1579907856,"remaining_time":0.9705148257},
{"learn":[0.1183551496],"iteration":14,"passed_time":0.1692487278,"remaining_time":0.9590761244},
{"learn":[0.1153633255],"iteration":15,"passed_time":0.1766583311,"remaining_time":0.9274562383},
{"learn":[0.1138449458],"iteration":16,"passed_time":0.1842304952,"remaining_time":0.8994783001},
{"learn":[0.1128659374],"iteration":17,"passed_time":0.1916410607,"remaining_time":0.8730314985},
{"learn":[0.1124104964],"iteration":18,"passed_time":0.1994193146,"remaining_time":0.8501560253},
{"learn":[0.1122572933],"iteration":19,"passed_time":0.2050983672,"remaining_time":0.8203934689},
{"learn":[0.1107194413],"iteration":20,"passed_time":0.21154724,"remaining_time":0.7958205695},
{"learn":[0.11018232],"iteration":21,"passed_time":0.2196790279,"remaining_time":0.778862008},
{"learn":[0.1095452961],"iteration":22,"passed_time":0.2271515717,"remaining_time":0.7604639573},
{"learn":[0.1077262765],"iteration":23,"passed_time":0.2337823507,"remaining_time":0.7403107772},
{"learn":[0.1055301983],"iteration":24,"passed_time":0.2407233641,"remaining_time":0.7221700924},
{"learn":[0.1038287244],"iteration":25,"passed_time":0.2479564476,"remaining_time":0.7057221971},
{"learn":[0.1027830945],"iteration":26,"passed_time":0.2547607576,"remaining_time":0.688797604},
{"learn":[0.1007776558],"iteration":27,"passed_time":0.2614085233,"remaining_time":0.6721933456},
{"learn":[0.100219576],"iteration":28,"passed_time":0.2685169335,"remaining_time":0.6574035268},
{"learn":[0.09993608503],"iteration":29,"passed_time":0.2759663359,"remaining_time":0.6439214504},
{"learn":[0.09898990775],"iteration":30,"passed_time":0.2835008141,"remaining_time":0.631017941},
{"learn":[0.09868702072],"iteration":31,"passed_time":0.2904382677,"remaining_time":0.6171813188},
{"learn":[0.09790568694],"iteration":32,"passed_time":0.29767185,"remaining_time":0.6043640591},
{"learn":[0.0965828053],"iteration":33,"passed_time":0.3046377348,"remaining_time":0.5913556028},
{"learn":[0.09471950321],"iteration":34,"passed_time":0.3113106767,"remaining_time":0.5781483997},
{"learn":[0.09373696072],"iteration":35,"passed_time":0.318454429,"remaining_time":0.5661412071},
{"learn":[0.0928478435],"iteration":36,"passed_time":0.32572501,"remaining_time":0.5546128549},
{"learn":[0.09148979907],"iteration":37,"passed_time":0.3330404539,"remaining_time":0.5433817932},
{"learn":[0.09148196074],"iteration":38,"passed_time":0.3381431567,"remaining_time":0.5288905785},
{"learn":[0.09144303097],"iteration":39,"passed_time":0.3440266637,"remaining_time":0.5160399956},
{"learn":[0.09094373812],"iteration":40,"passed_time":0.3511301935,"remaining_time":0.5052849126},
{"learn":[0.08966701048],"iteration":41,"passed_time":0.358647239,"remaining_time":0.4952747587},
{"learn":[0.08803077551],"iteration":42,"passed_time":0.3658912277,"remaining_time":0.4850186042},
{"learn":[0.08592866062],"iteration":43,"passed_time":0.3729189191,"remaining_time":0.4746240789},
{"learn":[0.08491037388],"iteration":44,"passed_time":0.3800811374,"remaining_time":0.4645436124},
{"learn":[0.08411214765],"iteration":45,"passed_time":0.3872642783,"remaining_time":0.4546145875},
{"learn":[0.08348550015],"iteration":46,"passed_time":0.3947092402,"remaining_time":0.4450976539},
{"learn":[0.08246944511],"iteration":47,"passed_time":0.4020965354,"remaining_time":0.43560458},
{"learn":[0.08196830639],"iteration":48,"passed_time":0.4091405818,"remaining_time":0.4258401974},
{"learn":[0.08168104347],"iteration":49,"passed_time":0.4160886911,"remaining_time":0.4160886911},
{"learn":[0.08130008412],"iteration":50,"passed_time":0.4233071468,"remaining_time":0.4067068665},
{"learn":[0.07981060908],"iteration":51,"passed_time":0.4305641072,"remaining_time":0.3974437913},
{"learn":[0.07921924608],"iteration":52,"passed_time":0.4375435504,"remaining_time":0.3880103183},
{"learn":[0.07838371329],"iteration":53,"passed_time":0.4447412307,"remaining_time":0.378853641},
{"learn":[0.07736095963],"iteration":54,"passed_time":0.4517386471,"remaining_time":0.3696043477},
{"learn":[0.07616752878],"iteration":55,"passed_time":0.4581486613,"remaining_time":0.3599739482},
{"learn":[0.07612795647],"iteration":56,"passed_time":0.465883494,"remaining_time":0.3514559692},
{"learn":[0.074835091],"iteration":57,"passed_time":0.4733840223,"remaining_time":0.3427953265},
{"learn":[0.07387791354],"iteration":58,"passed_time":0.4808963352,"remaining_time":0.3341821991},
{"learn":[0.07323021563],"iteration":59,"passed_time":0.4886149569,"remaining_time":0.3257433046},
{"learn":[0.07245293661],"iteration":60,"passed_time":0.4957806361,"remaining_time":0.3169745051},
{"learn":[0.07213877258],"iteration":61,"passed_time":0.5034035439,"remaining_time":0.308537656},
{"learn":[0.07172293766],"iteration":62,"passed_time":0.5107095154,"remaining_time":0.299940509},
{"learn":[0.07167630301],"iteration":63,"passed_time":0.5184465469,"remaining_time":0.2916261826},
{"learn":[0.07163849858],"iteration":64,"passed_time":0.5283562926,"remaining_time":0.2844995421},
{"learn":[0.07123123224],"iteration":65,"passed_time":0.5361066591,"remaining_time":0.2761761577},
{"learn":[0.06999730821],"iteration":66,"passed_time":0.5441582699,"remaining_time":0.2680182523},
{"learn":[0.06924436322],"iteration":67,"passed_time":0.5525100182,"remaining_time":0.2600047145},
{"learn":[0.06846337864],"iteration":68,"passed_time":0.5602840623,"remaining_time":0.2517218251},
{"learn":[0.06777184728],"iteration":69,"passed_time":0.5703399333,"remaining_time":0.2444314},
{"learn":[0.0676090252],"iteration":70,"passed_time":0.580201464,"remaining_time":0.2369836966},
{"learn":[0.06723047054],"iteration":71,"passed_time":0.5881380661,"remaining_time":0.228720359},
{"learn":[0.06721561831],"iteration":72,"passed_time":0.5963464279,"remaining_time":0.220566487},
{"learn":[0.06672293168],"iteration":73,"passed_time":0.6054229785,"remaining_time":0.2127161816},
{"learn":[0.06620828966],"iteration":74,"passed_time":0.6134696995,"remaining_time":0.2044898998},
{"learn":[0.06568408529],"iteration":75,"passed_time":0.6228719362,"remaining_time":0.1966964009},
{"learn":[0.06524492979],"iteration":76,"passed_time":0.6312673934,"remaining_time":0.1885603903},
{"learn":[0.06523405897],"iteration":77,"passed_time":0.639865629,"remaining_time":0.180474921},
{"learn":[0.06439827681],"iteration":78,"passed_time":0.6486278498,"remaining_time":0.1724200613},
{"learn":[0.0643764297],"iteration":79,"passed_time":0.6564811349,"remaining_time":0.1641202837},
{"learn":[0.0637876629],"iteration":80,"passed_time":0.6652016222,"remaining_time":0.1560349484},
{"learn":[0.06300172683],"iteration":81,"passed_time":0.6724436054,"remaining_time":0.1476095719},
{"learn":[0.06263773888],"iteration":82,"passed_time":0.6816780248,"remaining_time":0.1396208003},
{"learn":[0.06231830569],"iteration":83,"passed_time":0.6902075761,"remaining_time":0.1314681097},
{"learn":[0.06197128247],"iteration":84,"passed_time":0.6982819522,"remaining_time":0.1232262269},
{"learn":[0.06156208923],"iteration":85,"passed_time":0.7053885991,"remaining_time":0.1148307022},
{"learn":[0.06112192395],"iteration":86,"passed_time":0.7125335619,"remaining_time":0.1064705322},
{"learn":[0.06042697745],"iteration":87,"passed_time":0.7200642058,"remaining_time":0.09819057352},
{"learn":[0.06042146739],"iteration":88,"passed_time":0.727367724,"remaining_time":0.08989938162},
{"learn":[0.05993343775],"iteration":89,"passed_time":0.7348718883,"remaining_time":0.08165243204},
{"learn":[0.05940901671],"iteration":90,"passed_time":0.7415783218,"remaining_time":0.07334291095},
{"learn":[0.05916310276],"iteration":91,"passed_time":0.7483290543,"remaining_time":0.06507209168},
{"learn":[0.05878646216],"iteration":92,"passed_time":0.7552748682,"remaining_time":0.05684864599},
{"learn":[0.05878355513],"iteration":93,"passed_time":0.7624554202,"remaining_time":0.04866736725},
{"learn":[0.05804433521],"iteration":94,"passed_time":0.7705273525,"remaining_time":0.04055407118},
{"learn":[0.05803752773],"iteration":95,"passed_time":0.7775557028,"remaining_time":0.03239815428},
{"learn":[0.05707501162],"iteration":96,"passed_time":0.7846494018,"remaining_time":0.02426750727},
{"learn":[0.05688590543],"iteration":97,"passed_time":0.7920507993,"remaining_time":0.01616430203},
{"learn":[0.05595957584],"iteration":98,"passed_time":0.7994088916,"remaining_time":0.008074837289},
{"learn":[0.05576884424],"iteration":99,"passed_time":0.8069191096,"remaining_time":0}
]}